Metadata-Version: 2.4
Name: ezdb-utpal-raina
Version: 1.0.0
Summary: EzDB B-Class - Free & open source vector database for semantic search
Home-page: https://github.com/utpalraina/ezdb
Author: EzDB Team
Author-email: EzDB Team <hello@ezdb.io>
License: MIT
Project-URL: Homepage, https://github.com/utpalraina/ezdb
Project-URL: Documentation, https://github.com/utpalraina/ezdb#readme
Project-URL: Repository, https://github.com/utpalraina/ezdb
Project-URL: Bug Tracker, https://github.com/utpalraina/ezdb/issues
Keywords: vector database,semantic search,embeddings,AI,machine learning,similarity search
Classifier: Development Status :: 5 - Production/Stable
Classifier: Intended Audience :: Developers
Classifier: Intended Audience :: Science/Research
Classifier: Topic :: Database
Classifier: Topic :: Scientific/Engineering :: Artificial Intelligence
Classifier: License :: OSI Approved :: MIT License
Classifier: Programming Language :: Python :: 3
Classifier: Programming Language :: Python :: 3.8
Classifier: Programming Language :: Python :: 3.9
Classifier: Programming Language :: Python :: 3.10
Classifier: Programming Language :: Python :: 3.11
Classifier: Programming Language :: Python :: 3.12
Classifier: Operating System :: OS Independent
Requires-Python: >=3.8
License-File: LICENSE
Requires-Dist: numpy>=1.24.0
Requires-Dist: hnswlib>=0.8.0
Provides-Extra: server
Requires-Dist: fastapi>=0.104.0; extra == "server"
Requires-Dist: uvicorn[standard]>=0.24.0; extra == "server"
Requires-Dist: pydantic>=2.0.0; extra == "server"
Requires-Dist: python-multipart>=0.0.6; extra == "server"
Provides-Extra: embeddings
Requires-Dist: sentence-transformers>=2.2.0; extra == "embeddings"
Provides-Extra: openai
Requires-Dist: openai>=1.0.0; extra == "openai"
Provides-Extra: cohere
Requires-Dist: cohere>=4.0.0; extra == "cohere"
Provides-Extra: huggingface
Requires-Dist: transformers>=4.30.0; extra == "huggingface"
Requires-Dist: torch>=2.0.0; extra == "huggingface"
Provides-Extra: all
Requires-Dist: fastapi>=0.104.0; extra == "all"
Requires-Dist: uvicorn[standard]>=0.24.0; extra == "all"
Requires-Dist: pydantic>=2.0.0; extra == "all"
Requires-Dist: python-multipart>=0.0.6; extra == "all"
Requires-Dist: sentence-transformers>=2.2.0; extra == "all"
Provides-Extra: full
Requires-Dist: fastapi>=0.104.0; extra == "full"
Requires-Dist: uvicorn[standard]>=0.24.0; extra == "full"
Requires-Dist: pydantic>=2.0.0; extra == "full"
Requires-Dist: python-multipart>=0.0.6; extra == "full"
Requires-Dist: sentence-transformers>=2.2.0; extra == "full"
Requires-Dist: openai>=1.0.0; extra == "full"
Requires-Dist: cohere>=4.0.0; extra == "full"
Provides-Extra: dev
Requires-Dist: pytest>=7.0.0; extra == "dev"
Requires-Dist: pytest-cov>=4.0.0; extra == "dev"
Requires-Dist: black>=23.0.0; extra == "dev"
Requires-Dist: flake8>=6.0.0; extra == "dev"
Requires-Dist: mypy>=1.0.0; extra == "dev"
Dynamic: author
Dynamic: home-page
Dynamic: license-file
Dynamic: requires-python
